README.md
setup.py
giggity/__init__.py
giggity/giggity.py
giggity.egg-info/PKG-INFO
giggity.egg-info/SOURCES.txt
giggity.egg-info/dependency_links.txt
giggity.egg-info/entry_points.txt
giggity.egg-info/requires.txt
giggity.egg-info/top_level.txt