Metadata-Version: 2.1
Name: giggity
Version: 1.0.0
Summary: CLI Git Sleuth Tool
Home-page: https://github.com/needmorecowbell/giggity
Author: Adam Musciano
Author-email: amusciano@gmail.com
License: UNKNOWN
Platform: UNKNOWN
Classifier: Programming Language :: Python :: 3
Classifier: License :: OSI Approved :: MIT License
Requires-Python: >=3.6
